cleanroom/__init__.py
cleanroom/factory.py
cleanroom-0.4.2.dist-info/AUTHORS.rst
cleanroom-0.4.2.dist-info/LICENSE
cleanroom-0.4.2.dist-info/METADATA
cleanroom-0.4.2.dist-info/WHEEL
cleanroom-0.4.2.dist-info/top_level.txt
cleanroom-0.4.2.dist-info/RECORD
