Metadata-Version: 2.1
Name: cleanroom
Version: 0.4.2
Summary: None
Home-page: https://github.com/huntzhan/cleanroom
Author: Hunt Zhan
Author-email: huntzhan.dev@gmail.com
License: MIT license
Keywords: cleanroom
Platform: UNKNOWN
Classifier: Development Status :: 2 - Pre-Alpha
Classifier: Intended Audience :: Developers
Classifier: License :: OSI Approved :: MIT License
Classifier: Natural Language :: English
Classifier: Programming Language :: Python :: 3
Classifier: Programming Language :: Python :: 3.6
Classifier: Programming Language :: Python :: 3.7
Requires-Dist: tblib (==1.4.0)
